LICENSE
MANIFEST.in
README.rst
VERSION
setup.cfg
setup.py
bin/kine
bin/kine.bat
kinemathic/__init__.py
kinemathic/animation.py
kinemathic/resample.py
kinemathic.egg-info/PKG-INFO
kinemathic.egg-info/SOURCES.txt
kinemathic.egg-info/dependency_links.txt
kinemathic.egg-info/not-zip-safe
kinemathic.egg-info/requires.txt
kinemathic.egg-info/top_level.txt