Metadata-Version: 1.0
Name: kinemathic
Version: 0.2.0
Summary: Tool to generate kinematic displays
Home-page: http://github.com/dionresearch/kinemathic
Author: Francois Dion
Author-email: fdion@dionresearch.com
License: MIT
Platform: UNKNOWN
